shoots/__init__.py
shoots/jwt_client_auth_handler.py
shoots/jwt_server_auth.py
shoots/shoots_client.py
shoots/shoots_server.py
tests/__init__.py
tests/base_test.py
tests/insecure_test.py
tests/jwt_test.py
tests/large_datasets_test.py
tests/run_tests.py
tests/tls_test.py
shoots-0.1.1.dist-info/LICENSE
shoots-0.1.1.dist-info/METADATA
shoots-0.1.1.dist-info/WHEEL
shoots-0.1.1.dist-info/entry_points.txt
shoots-0.1.1.dist-info/top_level.txt
shoots-0.1.1.dist-info/RECORD
