Metadata-Version: 2.1
Name: shoots
Version: 0.1.1
Summary: A Pandas dataframe data lake
Home-page: https://github.com/rickspencer3/shoots
Author: Rick Spencer
Author-email: richard.linger.spencer.3@gmail.com
Classifier: Programming Language :: Python :: 3
Classifier: License :: OSI Approved :: MIT License
Classifier: Operating System :: OS Independent
License-File: LICENSE
Requires-Dist: pyarrow
Requires-Dist: datafusion
Requires-Dist: jwt
Requires-Dist: pydantic
Requires-Dist: pydantic-settings
Requires-Dist: pandas
Provides-Extra: test
Requires-Dist: pydantic ; extra == 'test'
Requires-Dist: pydantic-settings ; extra == 'test'
Requires-Dist: pandas ; extra == 'test'
